CHANGELOG.rst
Dockerfile
LICENSE
MANIFEST.in
README.rst
requirements.txt
setup.py
docs/Makefile
docs/api.rst
docs/conf.py
docs/index.rst
docs/introduction.rst
docs/license.rst
docs/newfunc.rst
docs/requirements-rtd.txt
docs/tutorial-docker.rst
docs/tutorial.rst
docs/_build/html/_images/amp-ion.svg
docs/_build/html/_images/amp.svg
docs/_build/html/_images/ethanol.png
docs/_build/html/_images/l-valine-zwitterion.svg
docs/_build/html/_images/l-valine.svg
docs/_build/html/_images/vitaminC.png
docs/_build/html/_sources/api.rst.txt
docs/_build/html/_sources/index.rst.txt
docs/_build/html/_sources/introduction.rst.txt
docs/_build/html/_sources/license.rst.txt
docs/_build/html/_sources/newfunc.rst.txt
docs/_build/html/_sources/requirements-rtd.txt
docs/_build/html/_sources/tutorial-docker.rst.txt
docs/_build/html/_sources/tutorial.rst.txt
docs/_build/html/_static/amp-ion.svg
docs/_build/html/_static/amp.svg
docs/_build/html/_static/ethanol.png
docs/_build/html/_static/file.png
docs/_build/html/_static/l-valine-zwitterion.svg
docs/_build/html/_static/l-valine.svg
docs/_build/html/_static/minus.png
docs/_build/html/_static/plus.png
docs/_build/html/_static/vitaminC.png
docs/_build/html/_static/fonts/fontawesome-webfont.svg
docs/_static/amp-ion.svg
docs/_static/amp.svg
docs/_static/ethanol.png
docs/_static/l-valine-zwitterion.svg
docs/_static/l-valine.svg
docs/_static/vitaminC.png
isoenum/__init__.py
isoenum/__main__.py
isoenum/api.py
isoenum/chemspider.py
isoenum/cli.py
isoenum/conf.py
isoenum/exceptions.py
isoenum/fileio.py
isoenum/iso_property.py
isoenum/labeling.py
isoenum/nmr.py
isoenum/openbabel.py
isoenum/utils.py
isoenum.egg-info/PKG-INFO
isoenum.egg-info/SOURCES.txt
isoenum.egg-info/dependency_links.txt
isoenum.egg-info/entry_points.txt
isoenum.egg-info/requires.txt
isoenum.egg-info/top_level.txt
isoenum/config_files/formats.json
isoenum/config_files/isotopes.json